{
  "generated_at": "Wednesday 10 June 2026 – 18:39",
  "session": "chiusura",
  "commentary": "Dati di mercato aggiornati. Analisi AI temporaneamente non disponibile.",
  "assets": [
    {
      "symbol": "^GSPC",
      "name": "S&P 500",
      "category": "equity",
      "emoji": "🇺🇸",
      "current": 7328.48,
      "currency": "USD",
      "day_pct": -0.79,
      "week_pct": -2.98,
      "month_pct": -1.14
    },
    {
      "symbol": "IWDA.AS",
      "name": "MSCI World",
      "category": "equity",
      "emoji": "🌍",
      "current": 120.74,
      "currency": "EUR",
      "day_pct": -0.09,
      "week_pct": -2.56,
      "month_pct": 0.68
    },
    {
      "symbol": "EIMI.MI",
      "name": "EIMI MI",
      "category": "equity",
      "emoji": "🌏",
      "current": 45.945,
      "currency": "EUR",
      "day_pct": -0.34,
      "week_pct": -6.08,
      "month_pct": -2.68
    },
    {
      "symbol": "XDWT.DE",
      "name": "XDWT Tech",
      "category": "equity",
      "emoji": "💻",
      "current": 117.58,
      "currency": "EUR",
      "day_pct": -0.58,
      "week_pct": -8.7,
      "month_pct": 1.26
    },
    {
      "symbol": "CL=F",
      "name": "Petrolio WTI",
      "category": "commodity",
      "emoji": "🛢️",
      "current": 91.0,
      "currency": "USD",
      "day_pct": 3.17,
      "week_pct": -5.23,
      "month_pct": -7.21
    },
    {
      "symbol": "GC=F",
      "name": "Oro",
      "category": "commodity",
      "emoji": "🥇",
      "current": 4149.7,
      "currency": "USD",
      "day_pct": -2.59,
      "week_pct": -6.47,
      "month_pct": -12.06
    },
    {
      "symbol": "SI=F",
      "name": "Argento",
      "category": "commodity",
      "emoji": "🥈",
      "current": 65.065,
      "currency": "USD",
      "day_pct": -0.04,
      "week_pct": -11.45,
      "month_pct": -23.89
    },
    {
      "symbol": "BTC-USD",
      "name": "Bitcoin",
      "category": "crypto",
      "emoji": "₿",
      "current": 62247.66,
      "currency": "USD",
      "day_pct": 0.98,
      "week_pct": 2.17,
      "month_pct": -24.22
    },
    {
      "symbol": "SOL-USD",
      "name": "Solana",
      "category": "crypto",
      "emoji": "◎",
      "current": 64.85,
      "currency": "USD",
      "day_pct": -0.17,
      "week_pct": 2.15,
      "month_pct": -32.75
    },
    {
      "symbol": "EURUSD=X",
      "name": "EUR/USD",
      "category": "forex",
      "emoji": "💶",
      "current": 1.1562,
      "currency": "USD",
      "day_pct": 0.29,
      "week_pct": -0.52,
      "month_pct": -1.76
    },
    {
      "symbol": "^TNX",
      "name": "Bond US 10Y",
      "category": "bond",
      "emoji": "📊",
      "current": 4.53,
      "currency": "USD",
      "day_pct": 0.04,
      "week_pct": 0.87,
      "month_pct": 2.72
    }
  ]
}